setup.py
pdnsapi/__init__.py
pdnsapi/api.py
pdnsapi/exceptions.py
pdnsapi.egg-info/PKG-INFO
pdnsapi.egg-info/SOURCES.txt
pdnsapi.egg-info/dependency_links.txt
pdnsapi.egg-info/not-zip-safe
pdnsapi.egg-info/requires.txt
pdnsapi.egg-info/top_level.txt