Metadata-Version: 1.0
Name: pdnsapi
Version: 0.2.1
Summary: Library for connecting to PowerDNS 3.4 REST API
Home-page: UNKNOWN
Author: Erik Lundberg
Author-email: lundbergerik@gmail.com
License: UNKNOWN
Platform: UNKNOWN
